{
  "indexes": [
    {
      "collectionGroup": "tournaments",
      "queryScope": "COLLECTION",
      "fields": [
        { "fieldPath": "status", "order": "ASCENDING" },
        { "fieldPath": "createdAt", "order": "DESCENDING" }
      ]
    },
    {
      "collectionGroup": "friendships",
      "queryScope": "COLLECTION",
      "fields": [
        { "fieldPath": "users", "arrayConfig": "CONTAINS" },
        { "fieldPath": "status", "order": "ASCENDING" }
      ]
    },
    {
      "collectionGroup": "wheels",
      "queryScope": "COLLECTION",
      "fields": [
        { "fieldPath": "ownerId", "order": "ASCENDING" },
        { "fieldPath": "createdAt", "order": "DESCENDING" }
      ]
    },
    {
      "collectionGroup": "notifications",
      "queryScope": "COLLECTION",
      "fields": [
        { "fieldPath": "userId", "order": "ASCENDING" },
        { "fieldPath": "createdAt", "order": "DESCENDING" }
      ]
    }
  ],
  "fieldOverrides": [
    {
      "collectionGroup": "members",
      "fieldPath": "uid",
      "indexes": [
        { "queryScope": "COLLECTION", "order": "ASCENDING" },
        { "queryScope": "COLLECTION_GROUP", "order": "ASCENDING" }
      ]
    },
    {
      "collectionGroup": "users",
      "fieldPath": "totalWins",
      "indexes": [
        { "queryScope": "COLLECTION", "order": "ASCENDING" },
        { "queryScope": "COLLECTION", "order": "DESCENDING" }
      ]
    },
    {
      "collectionGroup": "users",
      "fieldPath": "totalGoalsScored",
      "indexes": [
        { "queryScope": "COLLECTION", "order": "ASCENDING" },
        { "queryScope": "COLLECTION", "order": "DESCENDING" }
      ]
    },
    {
      "collectionGroup": "users",
      "fieldPath": "tournamentsWon",
      "indexes": [
        { "queryScope": "COLLECTION", "order": "ASCENDING" },
        { "queryScope": "COLLECTION", "order": "DESCENDING" }
      ]
    },
    {
      "collectionGroup": "matches",
      "fieldPath": "homeUid",
      "indexes": [
        { "queryScope": "COLLECTION", "order": "ASCENDING" },
        { "queryScope": "COLLECTION_GROUP", "order": "ASCENDING" }
      ]
    },
    {
      "collectionGroup": "matches",
      "fieldPath": "awayUid",
      "indexes": [
        { "queryScope": "COLLECTION", "order": "ASCENDING" },
        { "queryScope": "COLLECTION_GROUP", "order": "ASCENDING" }
      ]
    }
  ]
}
